{"cameraMode":{"drawMode":31,"name":"Sprite Mask","section":"Miscellaneous"},"sceneLighting":false,"audioPlay":false,"sceneViewState":{"m_AlwaysRefresh":false,"showFog":true,"showSkybox":false,"showFlares":true,"showImageEffects":true,"showParticleSystems":true,"showVisualEffectGraphs":true,"m_FxEnabled":true},"in2DMode":false,"pivot":{"x":6.360000133514404,"y":1.350000023841858,"z":0.0},"rotation":{"x":-0.0058351242914795879,"y":0.993971049785614,"z":-0.08669422566890717,"w":-0.06689898669719696},"size":7.0276336669921879,"orthographic":true}